setup.py
easyEmail/__init__.py
easyEmail/easyEmail.py
easyEmail/testeasyEmail.py
emailEasy.egg-info/PKG-INFO
emailEasy.egg-info/SOURCES.txt
emailEasy.egg-info/dependency_links.txt
emailEasy.egg-info/top_level.txt