Metadata-Version: 1.0
Name: emailEasy
Version: 1.0
Summary: Make email easier.
Home-page: https://github.com/zhuangchaoxi/easyEmail
Author: zhuangchaoxi
Author-email: zhuangchaoxi@kaike.la
License: MIT License
Keywords: emailEasy,egg
Platform: any
